Workbook

Sheet readme
D3: Sustainability Reporting Navigator
D4: CSRD Report Archive
D6: Welcome to the SRN CSRD Report Archive. On these sheets, we want to enable stakeholders of sustainability reporting
D7: to learn about and share annual reports prepared in accordance with the CSRD.
D9: Find our new interactive dashboard here!
D13: In the csrd sheet, you find a list of CSRD-compliant annual reports published for fiscal year 2024. Feel free to add new reports,
D14: we will approve them and mark those in gray. Please be reminded that we exert best effort to check for CSRD compliance
D15: but do not make any audit, verification, or assurance.
D17: In the non-csrd (other) reports sheet, feel free to mark best-practice reports that do not fully claim to follow the CSRD.
D18: From time to time, we move non-compliant reports from csrd here.
D20: Join our newsletter to stay up to date for new reports!
D22: https://sustainabilityreportingnavigator.com/

Sheet csrd
A1: Click here for our interactive Dashboard!
A2: Add New Reports Down Below (english versions only) ⬇️
A3: verified | B3: srn_id | C3: company | D3: isin | E3: country | F3: publication date | G3: claim full CSRD compliance | H3: auditor | I3: start PDF | J3: end PDF | K3: pages PDF | L3: link | M3: ESEF- tagged | N3: SASB industry (SICS® Industries) | O3: SASB sector (SICS® Sectors)
A4: yes | B4: tVkXa1OoYn | C4: Netcompany | D4: DK0060952919 | E4: Denmark | F4: 45686 | G4: TRUE | H4: EY | I4: 62 | J4: 154 | K4: =J4-I4+1 -> 93 | L4: https://netcompany.com/investor/annual-report/ | N4: Internet Media & Services | O4: {=_xludf.XLOOKUP(csrd!N4,industries!A:A,industries!B:B,"")} -> #NAME?
A5: yes | B5: 4P9CZx30gn | C5: Tryg | D5: DK0060636678 | E5: Denmark | F5: 45680 | G5: TRUE | H5: PwC | I5: 53 | J5: 131 | K5: =J5-I5+1 -> 79 | L5: https://tryg.com/sites/tryg.com/files/2025-01/Annual%20Report%202024%20-%20TRYG%20A_S.pdf | N5: Insurance | O5: {=_xludf.XLOOKUP(csrd!N5,industries!A:A,industries!B:B,"")} -> #NAME?
A6: yes | B6: u63Ki9uBLF | C6: DSV Panalpina | D6: DK0060079531 | E6: Denmark | F6: 45692 | G6: TRUE | H6: PwC | I6: 42 | J6: 84 | K6: =J6-I6+1 -> 43 | L6: https://investor.dsv.com/static-files/d34d3dfc-e1fe-4a25-a2c8-9d736830025a | N6: Air Freight & Logistics | O6: {=_xludf.XLOOKUP(csrd!N6,industries!A:A,industries!B:B,"")} -> #NAME?
A7: yes | B7: PtoavXijSQ | C7: Lundbeck | D7: DK0061804697 | E7: Denmark | F7: 45692 | G7: TRUE | H7: PwC | I7: 59 | J7: 144 | K7: =J7-I7+1 -> 86 | L7: https://www.lundbeck.com/content/dam/lundbeck-com/masters/global-site/global-site/investors/2024/fy24/Lundbeck%20Annual%20Report%202024.pdf | N7: Biotechnology & Pharmaceuticals | O7: {=_xludf.XLOOKUP(csrd!N7,industries!A:A,industries!B:B,"")} -> #NAME?
A8: yes | B8: g5GXXjndDy | C8: Vestas | D8: DK0061539921 | E8: Denmark | F8: 45693 | G8: TRUE | H8: Deloitte | I8: 51 | J8: 132 | K8: =J8-I8+1 -> 82 | L8: https://www.vestas.com/content/dam/vestas-com/global/en/investor/reports-and-presentations/financial/2024/fy-2024/Vestas%20Annual%20Report%202024.pdf.coredownload.inline.pdf | N8: Wind Technology & Project Developers | O8: {=_xludf.XLOOKUP(csrd!N8,industries!A:A,industries!B:B,"")} -> #NAME?
A9: yes | B9: lvCwvKME40 | C9: Demant | D9: DK0060738599 | E9: Denmark | F9: 45693 | G9: TRUE | H9: PwC | I9: 52 | J9: 117 | K9: =J9-I9+1 -> 66 | L9: https://assets-we.cas.dgs.com/-/media/demant/shared/new-library-2022/financial-reports/annual-report-english/demant-annual-report-2024_2.pdf?la=en&rev=0487&hash=BF20FE17B1586ABE0B06D808F899EC67 | N9: Medical Equipment & Supplies | O9: {=_xludf.XLOOKUP(csrd!N9,industries!A:A,industries!B:B,"")} -> #NAME?
A10: yes | B10: kSkHNYvVe0 | C10: Pandora | D10: DK0060252690 | E10: Denmark | F10: 45693 | G10: TRUE | H10: EY | I10: 47 | J10: 101 | K10: =J10-I10+1 -> 55 | L10: https://ml-eu.globenewswire.com/Resource/Download/edd04a03-bc89-4cc9-8924-4439f5efd4b0 | N10: Apparel, Accessories & Footwear | O10: {=_xludf.XLOOKUP(csrd!N10,industries!A:A,industries!B:B,"")} -> #NAME?
A11: yes | B11: 8kFxYzPwEF | C11: Novo Nordisk | D11: DK0062498333 | E11: Denmark | F11: 45693 | G11: TRUE | H11: Deloitte | I11: 46 | J11: 99 | K11: =J11-I11+1 -> 54 | L11: https://www.novonordisk.com/content/dam/nncorp/global/en/investors/irmaterial/annual_report/2025/novo-nordisk-annual-report-2024.pdf | N11: Biotechnology & Pharmaceuticals | O11: {=_xludf.XLOOKUP(csrd!N11,industries!A:A,industries!B:B,"")} -> #NAME?
A12: yes | B12: dUq3yzjw72 | C12: Ringkjøbing Landbobank | D12: DK0060854669 | E12: Denmark | F12: 45693 | G12: TRUE | H12: PwC | I12: 53 | J12: 151 | K12: =J12-I12+1 -> 99 | L12: https://attachment.news.eu.nasdaq.com/aba5d8f5b0b18efd66154512ade0b124d | N12: Commercial Banks | O12: {=_xludf.XLOOKUP(csrd!N12,industries!A:A,industries!B:B,"")} -> #NAME?
A13: yes | B13: JKZH9DIUvs | C13: Nykredit | D13: DK000954829 | E13: Denmark | F13: 45693 | G13: TRUE | H13: EY | I13: 30 | J13: 128 | K13: =J13-I13+1 -> 99 | L13: https://www.nykredit.com/siteassets/ir/files/financial-reporting/financial-reports/nykredit/2024/nykredit_q4_24_2025-02-05_en.pdf | N13: Commercial Banks | O13: {=_xludf.XLOOKUP(csrd!N13,industries!A:A,industries!B:B,"")} -> #NAME?
A14: yes | B14: 3Q1YxwYAeJ | C14: Spar Nord Bank | D14: DK0060036564 | E14: Denmark | F14: 45693 | G14: TRUE | H14: Deloitte | I14: 52 | J14: 111 | K14: =J14-I14+1 -> 60 | L14: https://attachment.news.eu.nasdaq.com/a264f5d299b19a040d919cc23445a0fcb | N14: Commercial Banks | O14: {=_xludf.XLOOKUP(csrd!N14,industries!A:A,industries!B:B,"")} -> #NAME?
A15: yes | B15: wZUyxMROr4 | C15: TomTom | D15: NL0013332471 | E15: Netherlands | F15: 45693 | G15: TRUE | H15: PwC | I15: 62 | J15: 100 | K15: =J15-I15+1 -> 39 | L15: https://corporate.tomtom.com/static-files/23910bbd-84e1-401d-8bf1-037fe9031d84 | N15: Internet Media & Services | O15: {=_xludf.XLOOKUP(csrd!N15,industries!A:A,industries!B:B,"")} -> #NAME?
... A246: yes | B246: 0FjvYICMi6 | C246: Vandemoortele | D246: n.a. | E246: Belgium | F246: 45744 | G246: TRUE | H246: Deloitte | I246: 47 | J246: 169 | K246: =J246-I246+1 -> 123 | L246: https://vandemoortele.com/sites/default/files/2025-03/EN_2024_AnnualIntegratedReport_Vandemoortele_1.pdf | N246: Processed Foods | O246: {=_xludf.XLOOKUP(csrd!N246,industries!A:A,industries!B:B,"")} -> #NAME?
A247: yes | B247: n4vbWlOuws | C247: Jungheinrich | D247: DE0006219934 | E247: Germany | F247: 45743 | G247: TRUE | H247: PwC | I247: 36 | J247: 110 | K247: =J247-I247+1 -> 75 | L247: https://media-live2.prod.scw.jungheinrichcloud.com/resource/blob/1945362/b99eaa2a05fb89cc1a9ba7e22002593e/download-jungheinrich-geschaeftsbericht-2024-data.pdf | M247: no | N247: Industrial Machinery & Goods | O247: {=_xludf.XLOOKUP(csrd!N247,industries!A:A,industries!B:B,"")} -> #NAME?
A248: yes | B248: lqrmGcWO4a | C248: Enagas | D248: ES0130960018 | E248: Spain | F248: 45730 | G248: TRUE | H248: EY | I248: 21 | J248: 238 | K248: =J248-I248+1 -> 218 | L248: https://www.enagas.es/content/dam/enagas/en/files/enagas-communication-room/publications/informe-anual/Annual-Report-2024-Enagas.pdf | N248: Oil & Gas – Midstream | O248: {=_xludf.XLOOKUP(csrd!N248,industries!A:A,industries!B:B,"")} -> #NAME?
A249: yes | B249: EKxsPTxgzi | C249: Knorr-Bremse | D249: DE000KBX1006 | E249: Germany | F249: 45736 | G249: TRUE | H249: KPMG | I249: 53 | J249: 131 | K249: =J249-I249+1 -> 79 | L249: https://ir-api.eqs.com/media/document/055f8df8-0727-4d65-968e-ffb3b7b87a35/assets/Knorr-Bremse_AG_Geschaeftsbericht_2024_safe.pdf?disposition=inline | N249: Industrial Machinery & Goods | O249: {=_xludf.XLOOKUP(csrd!N249,industries!A:A,industries!B:B,"")} -> #NAME?
A250: yes | B250: qDxh27letu | C250: Wirtualna Polska Holding | D250: PLWRTPL00027 | E250: Poland | F250: 45749 | G250: TRUE | H250: PwC | I250: 90 | J250: 176 | K250: =J250-I250+1 -> 87 | L250: https://holding.wpcdn.pl/uploader/Managements_report_2024.pdf?cEg=olmFE4%2BOw0OPx4ICQUVTVZPXA9dVlVPQ04eGw0ZBghPVU4OV1tdDg5UXFpYWFkOVw9ZXVxYCVUJVl1cDg9cWglYVlZZWlpcXApXXltcVlhdV1xaW1YbXE5BTRgEAgkeGw0AH05XXltZXVRbXlpcEg | N250: Internet Media & Services | O250: {=_xludf.XLOOKUP(csrd!N250,industries!A:A,industries!B:B,"")} -> #NAME?
A251: yes | B251: aPMJzQr4ka | C251: Stedin | D251: n.a. | E251: Netherlands | F251: 45747 | G251: TRUE | H251: Deloitte | I251: 119 | J251: 179 | K251: =J251-I251+1 -> 61 | L251: https://www.stedingroep.nl/-/media/project/groep/files/stedin_group_annual_report_2024.pdf | N251: Electric Utilities & Power Generators | O251: {=_xludf.XLOOKUP(csrd!N251,industries!A:A,industries!B:B,"")} -> #NAME?
A252: yes | B252: OYQSokOV9z | C252: LPP | D252: PLLPP0000011 | E252: Poland | F252: 45750 | G252: TRUE | H252: Grant Thornton | I252: 58 | J252: 159 | K252: =J252-I252+1 -> 102 | L252: https://wwwlpp62711ea95a.blob.core.windows.net/blobwwwlpp62711ea95a/wp-content/uploads/2025/04/Consolidated-annual-report-of-LPP-SA-Group-for-2024.pdf | N252: Apparel, Accessories & Footwear | O252: {=_xludf.XLOOKUP(csrd!N252,industries!A:A,industries!B:B,"")} -> #NAME?
A253: yes | B253: BjLX5KpKvC | C253: DZ BANK | D253: DE000DZ8L9C1 | E253: Germany | F253: 45744 | G253: TRUE | H253: PwC | I253: 198 | J253: 517 | K253: =J253-I253+1 -> 320 | L253: https://annualreport.dzbank.com/sites/default/files/2025-03/DZBANK_Group_AR2024.pdf | N253: Commercial Banks | O253: {=_xludf.XLOOKUP(csrd!N253,industries!A:A,industries!B:B,"")} -> #NAME?
A254: yes | B254: YhaOkDwnU0 | C254: Bank Polska Kasa Opieki | D254: PLPEKAO00016 | E254: Poland | F254: 45715 | G254: TRUE | H254: PwC | I254: 125 | J254: 298 | K254: =J254-I254+1 -> 174 | L254: https://www.pekao.com.pl/dam/jcr:4508067b-d2e6-4771-a4e0-0ef4ebfffdad/Report_on_the_Activities_Bank_Pekao_Group_RR2024.pdf | N254: Commercial Banks | O254: {=_xludf.XLOOKUP(csrd!N254,industries!A:A,industries!B:B,"")} -> #NAME?
A255: yes | B255: TYF5vX3urn | C255: Argenx | D255: NL0010832176 | E255: Netherlands | F255: 45736 | G255: TRUE | H255: Deloitte | I255: 305 | J255: 374 | K255: =J255-I255+1 -> 70 | L255: https://argenx.com/content/dam/argenx-corp/media-documents/argenx-Integrated_Annual_Report_2024-PDF_print_1.pdf.coredownload.inline.pdf | N255: Biotechnology & Pharmaceuticals | O255: {=_xludf.XLOOKUP(csrd!N255,industries!A:A,industries!B:B,"")} -> #NAME?
A256: yes | B256: TrrSjZsdOJ | C256: Assa Abloy | D256: SE0007100581 | E256: Sweden | F256: 45728 | G256: TRUE | H256: EY | I256: 62 | J256: 111 | K256: =J256-I256+1 -> 50 | L256: https://www.assaabloy.com/group/en/documents/investors/annual-reports/2024/Annual%20Report%202024%20-%20for%20print.pdf | N256: Electrical & Electronic Equipment | O256: {=_xludf.XLOOKUP(csrd!N256,industries!A:A,industries!B:B,"")} -> #NAME?
A257: yes | B257: fxUUR2SsB1 | C257: Svenska Handelsbanken | D257: SE0007100599 | E257: Sweden | F257: 45714 | G257: TRUE | H257: Deloitte | I257: 256 | J257: 375 | K257: =J257-I257+1 -> 120 | L257: https://www.handelsbanken.com/tron/xgpu/info/contents/v1/document/72-263272 | N257: Commercial Banks | O257: {=_xludf.XLOOKUP(csrd!N257,industries!A:A,industries!B:B,"")} -> #NAME?
A258: yes | B258: z4BMjMxjqf | C258: DNB Bank | D258: NO0010161896 | E258: Norway | F258: 45730 | G258: TRUE | H258: EY | I258: 62 | J258: 208 | K258: =J258-I258+1 -> 147 | L258: https://www.ir.dnb.no/sites/default/files/pr/202503192798-2.pdf | N258: Commercial Banks | O258: {=_xludf.XLOOKUP(csrd!N258,industries!A:A,industries!B:B,"")} -> #NAME?
A259: yes | B259: mInQovzkad | C259: ASM International | D259: NL0000334118 | E259: Netherlands | F259: 45722 | G259: TRUE | H259: KPMG | I259: 56 | J259: 92 | K259: =J259-I259+1 -> 37 | L259: https://www.asm.com/media/3xuppljv/annual-report-2024-asm-final.pdf | N259: Semiconductors | O259: {=_xludf.XLOOKUP(csrd!N259,industries!A:A,industries!B:B,"")} -> #NAME?
... A338: yes | B338: 9q0cegeoao | C338: Clariane | D338: FR0010386334 | E338: France | F338: 45748 | G338: TRUE | H338: Forvis Mazars | I338: 63 | J338: 253 | K338: =J338-I338+1 -> 191 | L338: https://www.clariane.com/sites/default/files/2025-04/CLARIANE_DEU_2024_UK.pdf | N338: Health Care Delivery | O338: {=_xludf.XLOOKUP(csrd!N338,industries!A:A,industries!B:B,"")} -> #NAME?
A339: yes | B339: mh35tlAQol | C339: Icade | D339: FR0000035081 | E339: France | F339: 45741 | G339: TRUE | H339: Forvis Mazars | I339: 99 | J339: 225 | K339: =J339-I339+1 -> 127 | L339: https://www.icade.fr/en/content/download/6671/file/universal-registration-document-2024.pdf | M339: no | N339: Real Estate | O339: {=_xludf.XLOOKUP(csrd!N339,industries!A:A,industries!B:B,"")} -> #NAME?
A340: yes | B340: rXD1xqtwsX | C340: Rapala VMC | D340: FI0009007355 | E340: Finland | F340: 45757 | G340: TRUE | H340: Deloitte | I340: 5 | J340: 30 | K340: =J340-I340+1 -> 26 | L340: https://investors.rapalavmc.com/files/documents/rapala-vmc-corporation-annual-report-2024.pdf | M340: no | N340: Toys & Sporting Goods | O340: {=_xludf.XLOOKUP(csrd!N340,industries!A:A,industries!B:B,"")} -> #NAME?
A341: yes | B341: L2WwgmSXD7 | C341: Salzgitter | D341: DE0006202005 | E341: Germany | F341: 45737 | G341: TRUE | H341: EY | I341: 103 | J341: 205 | K341: =J341-I341+1 -> 103 | L341: https://www.salzgitter-ag.com/fileadmin/finanzberichte/2024/gb2024/en/downloads/szag-ar2024-complete.pdf | N341: Iron & Steel Producers | O341: {=_xludf.XLOOKUP(csrd!N341,industries!A:A,industries!B:B,"")} -> #NAME?
A342: yes | B342: KWBTEL9EiU | C342: Legrand | D342: FR0010307819 | E342: France | F342: 45756 | G342: TRUE | H342: PwC & Forvis Mazars | I342: 97 | J342: 255 | K342: =J342-I342+1 -> 159 | L342: https://www.legrandgroup.com/sites/default/files/Documents_PDF_Legrand/Finance/2025/autre/Legrand_URD_2024_ENGLISH_1744198492.pdf | N342: Electrical & Electronic Equipment | O342: {=_xludf.XLOOKUP(csrd!N342,industries!A:A,industries!B:B,"")} -> #NAME?
A343: yes | B343: AogqC1qtk4 | C343: iliad | D343: FR0004035913 | E343: France | F343: 45771 | G343: TRUE | H343: Deloitte | I343: 89 | J343: 211 | K343: =J343-I343+1 -> 123 | L343: https://www.iliad.fr/media/ILIAD_URD_28042025_ENG_81bbd00ae3.pdf | N343: Telecommunication Services | O343: {=_xludf.XLOOKUP(csrd!N343,industries!A:A,industries!B:B,"")} -> #NAME?
A344: yes | B344: HryEauNCPi | C344: Worldline | D344: FR0011981968 | E344: France | F344: 45762 | G344: TRUE | H344: Deloitte | I344: 71 | J344: 196 | K344: =J344-I344+1 -> 126 | L344: https://investors.worldline.com/content/dam/investors-worldline-com/assets/documents/universal-registration-document/wordline_urd_2024.pdf | N344: Software & IT Services | O344: {=_xludf.XLOOKUP(csrd!N344,industries!A:A,industries!B:B,"")} -> #NAME?
A345: yes | B345: uCsSUP7PtG | C345: Ion Beam Applications (IBA) | D345: BE0003766806 | E345: Belgium | F345: 45775 | G345: TRUE | H345: PwC | I345: 175 | J345: 255 | K345: =J345-I345+1 -> 81 | L345: https://www.iba-worldwide.com/sites/default/files/2025-04/iba-annual-report_2024_en.pdf | N345: Medical Equipment & Supplies | O345: {=_xludf.XLOOKUP(csrd!N345,industries!A:A,industries!B:B,"")} -> #NAME?
A346: yes | B346: KMhBKQqyF4 | C346: Greenvolt-Energias Renovaveis | D346: PTGNV0AM0001 | E346: Portugal | F346: 45777 | G346: TRUE | H346: Deloitte | I346: 70 | J346: 262 | K346: =J346-I346+1 -> 193 | L346: https://www.cmvm.pt/PInstitucional/PdfVierInfPriv?Input=5EEB687C1F16B2C880DA7A040186F7EE308C4E5FE2ECF26305C5FC40C3725117 | N346: Electric Utilities & Power Generators | O346: {=_xludf.XLOOKUP(csrd!N346,industries!A:A,industries!B:B,"")} -> #NAME?
A347: yes | B347: zA3TA5ZeND | C347: The Navigator Company | D347: PTPTI0AM0006 | E347: Portugal | F347: 45777 | G347: TRUE | H347: KPMG | I347: 120 | J347: 299 | K347: =J347-I347+1 -> 180 | L347: https://www.thenavigatorcompany.com/wp-content/uploads/2025/04/RA2024-NVG-en.pdf | N347: Pulp & Paper Products | O347: {=_xludf.XLOOKUP(csrd!N347,industries!A:A,industries!B:B,"")} -> #NAME?
A348: yes | B348: MfPWfnj8nu | C348: Impresa SGPS | D348: PTIPR0AM0000 | E348: Portugal | F348: 45777 | G348: TRUE | H348: Deloitte | I348: 247 | J348: 327 | K348: =J348-I348+1 -> 81 | L348: https://sdistribution.impresa.pt/data/content/binaries/149/e2a/4010f45d-4401-4619-a7de-13789689966e/Relatorio-e-Contas-Impresa-2024_ENG.pdf | N348: Media & Entertainment | O348: {=_xludf.XLOOKUP(csrd!N348,industries!A:A,industries!B:B,"")} -> #NAME?
A349: yes | B349: iKMwiv7wV8 | C349: Altri SGPS | D349: PTALT0AE0002 | E349: Portugal | F349: 45750 | G349: TRUE | H349: EY | I349: 36 | J349: 174 | K349: =J349-I349+1 -> 139 | L349: https://www.cmvm.pt/PInstitucional/PdfVierInfPriv?Input=608D67E5442AC81836E5C9B31CAE7942F341CBDCA4DF224EF356EF9BFCB5C3DB | N349: Pulp & Paper Products | O349: {=_xludf.XLOOKUP(csrd!N349,industries!A:A,industries!B:B,"")} -> #NAME?
A350: yes | B350: EmTYJl8B62 | C350: Crédit Mutuel Arkéa | D350: n.a. | E350: France | F350: 45758 | G350: TRUE | H350: Deloitte & PwC | I350: 125 | J350: 290 | K350: =J350-I350+1 -> 166 | L350: https://www.cm-arkea.com/arkea/banque/upload/docs/application/pdf/2025-04/cma_urd_eng_2024.pdf | N350: Commercial Banks | O350: {=_xludf.XLOOKUP(csrd!N350,industries!A:A,industries!B:B,"")} -> #NAME?
A351: yes | B351: Jfwyiyd3Nk | C351: CUF | D351: n.a. | E351: Portugal | F351: 45770 | G351: TRUE | H351: Deloitte | I351: 40 | J351: 162 | K351: =J351-I351+1 -> 123 | L351: https://www.cuf.pt/media/53524/download?inline= | N351: Health Care Delivery | O351: {=_xludf.XLOOKUP(csrd!N351,industries!A:A,industries!B:B,"")} -> #NAME?
A352: yes | B352: w09CfRuq16 | C352: Jerónimo Martins SGPS | D352: PTJMT0AE0001 | E352: Portugal | F352: 45771 | G352: TRUE | H352: EY | I352: 242 | J352: 459 | K352: =J352-I352+1 -> 218 | L352: https://reports.jeronimomartins.com/annual-report/2024/_assets/downloads/entire-jeronimomartins-ar24.pdf | N352: Food Retailers & Distributors | O352: {=_xludf.XLOOKUP(csrd!N352,industries!A:A,industries!B:B,"")} -> #NAME?
... A460: yes | B460: sefctepTyI | C460: Amadeus Fire | D460: DE0005093108 | E460: Germany | F460: 45742 | G460: TRUE | H460: PwC | I460: 125 | J460: 212 | K460: =J460-I460+1 -> 88 | L460: https://group.amadeus-fire.de/wp-content/uploads/2025/04/Geschaeftsbericht-2024_EN-1.pdf | N460: Professional & Commercial Services | O460: {=_xludf.XLOOKUP(csrd!N460,industries!A:A,industries!B:B,"")} -> #NAME?
A461: yes | C461: Gaztransport Et Technigaz | D461: FR0011726835 | E461: France | F461: 45772 | G461: TRUE | H461: EY | I461: 81 | J461: 162 | K461: =J461-I461+1 -> 82 | L461: https://gtt.fr/sites/default/files/GTT%20-%20Universal%20Registration%20Document%20-%202024.pdf | N461: Engineering & Construction Services | O461: {=_xludf.XLOOKUP(csrd!N461,industries!A:A,industries!B:B,"")} -> #NAME?
A462: yes | C462: Gofore | D462: FI4000283130 | E462: Finland | F462: 45736 | G462: TRUE | H462: EY | I462: 18 | J462: 96 | K462: =J462-I462+1 -> 79 | L462: https://gofore.com/media/gofore-annual-report-2024.pdf | N462: Software & IT Services | O462: {=_xludf.XLOOKUP(csrd!N462,industries!A:A,industries!B:B,"")} -> #NAME?
A463: yes | C463: Grand City Properties | D463: LU0775917882 | E463: Luxembourg | F463: 45733 | G463: TRUE | H463: KPMG | I463: 38 | J463: 151 | K463: =J463-I463+1 -> 114 | L463: https://www.grandcityproperties.com/grandcityproperties.com/Data_Objects/Downloads/Financial_Reports/FY_2024_Financials/GCP_FY_2024.pdf | N463: Real Estate | O463: {=_xludf.XLOOKUP(csrd!N463,industries!A:A,industries!B:B,"")} -> #NAME?
A464: yes | C464: Guerbet | D464: FR0000032526 | E464: France | F464: 45742 | G464: TRUE | H464: Forvis Mazars & Crowe HAF | I464: 137 | J464: 258 | K464: =J464-I464+1 -> 122 | L464: https://www.guerbet.com/media/igwjfxp3/guerbet_deu-uk_2024-28-04-2025.pdf | N464: Medical Equipment & Supplies | O464: {=_xludf.XLOOKUP(csrd!N464,industries!A:A,industries!B:B,"")} -> #NAME?
A465: yes | C465: H Lundbeck | D465: DK0061804770 | E465: Denmark | F465: 45693 | G465: TRUE | H465: PwC | I465: 58 | J465: 144 | K465: =J465-I465+1 -> 87 | L465: https://www.lundbeck.com/content/dam/lundbeck-com/masters/global-site/annual-reporting/2024/Lundbeck_Annual_Report_2024.pdf | N465: Biotechnology & Pharmaceuticals | O465: {=_xludf.XLOOKUP(csrd!N465,industries!A:A,industries!B:B,"")} -> #NAME?
A466: yes | C466: Hafslund | D466: n.a. | E466: Norway | F466: 45750 | G466: TRUE | H466: PwC | I466: 41 | J466: 168 | K466: =J466-I466+1 -> 128 | L466: https://cdn.sanity.io/files/b0ujrg14/production/5d14623941e9345609131a818fd7989abc4d4387.pdf | N466: Electric Utilities & Power Generators | O466: {=_xludf.XLOOKUP(csrd!N466,industries!A:A,industries!B:B,"")} -> #NAME?
A467: yes | C467: Helaba | D467: n.a. | E467: Germany | F467: 45749 | G467: TRUE | H467: EY | I467: 65 | J467: 310 | K467: =J467-I467+1 -> 246 | L467: https://www.helaba.com/media/docs/int/investor-relations/publications/annual-reports/annual-reports-2024/annual-report-2024.pdf | N467: Commercial Banks | O467: {=_xludf.XLOOKUP(csrd!N467,industries!A:A,industries!B:B,"")} -> #NAME?
A468: yes | C468: ICA Gruppen | D468: SE0000652216 | E468: Sweden | F468: 45709 | G468: TRUE | H468: KPMG | I468: 76 | J468: 171 | K468: =J468-I468+1 -> 96 | L468: https://www.icagruppen.se/globalassets/xx.-arsredovisning-2024/250221_icagruppen_annual_report_2024.pdf | N468: Food Retailers & Distributors | O468: {=_xludf.XLOOKUP(csrd!N468,industries!A:A,industries!B:B,"")} -> #NAME?
A469: yes | C469: Ipsen | D469: FR0010259150 | E469: France | F469: 45754 | G469: TRUE | H469: PwC | I469: 166 | J469: 378 | K469: =J469-I469+1 -> 213 | L469: https://www.ipsen.com/websites/ipsen_com_v2/wp-content/uploads/2025/04/17154159/2024-Universal-Registration-Document.pdf | N469: Biotechnology & Pharmaceuticals | O469: {=_xludf.XLOOKUP(csrd!N469,industries!A:A,industries!B:B,"")} -> #NAME?
A470: yes | C470: JDE Peet's | D470: NL0014332678 | E470: Netherlands | F470: 45714 | G470: TRUE | H470: Deloitte | I470: 89 | J470: 220 | K470: =J470-I470+1 -> 132 | L470: https://www.jdepeets.com/siteassets/home/investors/annual-reports/jde-peets-annual-report-2024.pdf | N470: Non-Alcoholic Beverages | O470: {=_xludf.XLOOKUP(csrd!N470,industries!A:A,industries!B:B,"")} -> #NAME?
A471: yes | C471: Just Eat Takeaway.com | D471: NL0012015705 | E471: Netherlands | F471: 45714 | G471: TRUE | H471: EY | I471: 115 | J471: 157 | K471: =J471-I471+1 -> 43 | L471: https://s205.q4cdn.com/266311280/files/doc_financials/2024/ar/AR2024_JET-com.pdf | N471: Internet Media & Services | O471: {=_xludf.XLOOKUP(csrd!N471,industries!A:A,industries!B:B,"")} -> #NAME?
A472: yes | C472: Jyske Bank | D472: DK0010307958 | E472: Denmark | F472: 45714 | G472: TRUE | H472: EY | I472: 44 | J472: 151 | K472: =J472-I472+1 -> 108 | L472: https://jyskebank.com/wps/wcm/connect/jbc/db0d2cb1-8b88-4ddd-bbcc-b04dc5330d64/Jyske+Bank+Annual+Report+2024.pdf?MOD=AJPERES | N472: Commercial Banks | O472: {=_xludf.XLOOKUP(csrd!N472,industries!A:A,industries!B:B,"")} -> #NAME?
... A700: yes | C700: Teixeira Duarte | D700: PTTD10AM0000 | E700: Portugal | F700: 45771 | G700: TRUE | H700: Moore | I700: 32 | J700: 128 | K700: =J700-I700+1 -> 97 | L700: https://www.teixeiraduarte.pt/wp-content/uploads/2025/08/TDSA-RC-2024_EN-1.pdf | N700: Engineering & Construction Services | O700: {=_xludf.XLOOKUP(csrd!N700,industries!A:A,industries!B:B,"")} -> #NAME?
C701: Siemens | D701: DE0007236101 | E701: Germany | F701: 45994 | G701: TRUE | H701: PwC | I701: 144 | J701: 259 | K701: =J701-I701+1 -> 116 | L701: https://www.siemens.com/global/en/company/investor-relations/events-publications-ad-hoc/annualreports.html | N701: Electrical & Electronic Equipment | O701: {=_xludf.XLOOKUP(csrd!N701,industries!A:A,industries!B:B,"")} -> #NAME?
C702: Infineon Technologies | E702: Germany | F702: 45988 | G702: FALSE | H702: Deloitte | K702: =J702-I702+1 -> 1 | L702: https://www.infineon.com/assets/row/public/documents/corporate/company/sustainability/sustainability-at-infineon.pdf | N702: Semiconductors | O702: {=_xludf.XLOOKUP(csrd!N702,industries!A:A,industries!B:B,"")} -> #NAME?
C703: ELMOS SEMICONDUCTOR SE | E703: Germany | G703: FALSE | K703: =J703-I703+1 -> 1 | L703: https://www.elmos.com/fileadmin/elmos-website/about-us/investor_relations/corporate_governance/EZU/elmos_nachhaltigkeit_2024_e.pdf | N703: Semiconductors | O703: {=_xludf.XLOOKUP(csrd!N703,industries!A:A,industries!B:B,"")} -> #NAME?
C704: Colruyt Group | D704: BE0974256852 | E704: Belgium | F704: 45869 | G704: TRUE | H704: EY | I704: 127 | J704: 231 | K704: =J704-I704+1 -> 105 | L704: Annual report with sustainability reporting | Colruyt Group | N704: Food Retailers & Distributors | O704: {=_xludf.XLOOKUP(csrd!N704,industries!A:A,industries!B:B,"")} -> #NAME?
C705: Hrvatski Telekom | D705: HRHT00RA0005 | E705: Croatia | F705: 46105 | G705: TRUE | H705: Deloitte | I705: 37 | J705: 132 | K705: =J705-I705+1 -> 96 | L705: https://static.hrvatskitelekom.hr/webresources/tht/pdf/investitori/izvjesca/ANNUAL_REPORT_ENG_2025.pdf?_gl=1*1fcvs54*_up*MQ..*_ga*Nzc3MTIyNDguMTc3NDUxNzA2NQ..*_ga_85807GK74E*czE3NzQ1MTcwNjQkbzEkZzAkdDE3NzQ1MTcwNjQkajYwJGwwJGgxNTg4NzA2MTUx | N705: Telecommunication Services | O705: {=_xludf.XLOOKUP(csrd!N705,industries!A:A,industries!B:B,"")} -> #NAME?
G706: FALSE | K706: =J706-I706+1 -> 1 | O706: {=_xludf.XLOOKUP(csrd!N706,industries!A:A,industries!B:B,"")} -> #NAME?
G707: FALSE | K707: =J707-I707+1 -> 1 | O707: {=_xludf.XLOOKUP(csrd!N707,industries!A:A,industries!B:B,"")} -> #NAME?
G708: FALSE | K708: =J708-I708+1 -> 1 | O708: {=_xludf.XLOOKUP(csrd!N708,industries!A:A,industries!B:B,"")} -> #NAME?
G709: FALSE | K709: =J709-I709+1 -> 1 | O709: {=_xludf.XLOOKUP(csrd!N709,industries!A:A,industries!B:B,"")} -> #NAME?
G710: FALSE | K710: =J710-I710+1 -> 1 | O710: {=_xludf.XLOOKUP(csrd!N710,industries!A:A,industries!B:B,"")} -> #NAME?
G711: FALSE | K711: =J711-I711+1 -> 1 | O711: {=_xludf.XLOOKUP(csrd!N711,industries!A:A,industries!B:B,"")} -> #NAME?
G712: FALSE | K712: =J712-I712+1 -> 1 | O712: {=_xludf.XLOOKUP(csrd!N712,industries!A:A,industries!B:B,"")} -> #NAME?
G713: FALSE | K713: =J713-I713+1 -> 1 | O713: {=_xludf.XLOOKUP(csrd!N713,industries!A:A,industries!B:B,"")} -> #NAME?
G714: FALSE | K714: =J714-I714+1 -> 1 | O714: {=_xludf.XLOOKUP(csrd!N714,industries!A:A,industries!B:B,"")} -> #NAME?
G715: FALSE | K715: =J715-I715+1 -> 1 | O715: {=_xludf.XLOOKUP(csrd!N715,industries!A:A,industries!B:B,"")} -> #NAME?
G716: FALSE | K716: =J716-I716+1 -> 1 | O716: {=_xludf.XLOOKUP(csrd!N716,industries!A:A,industries!B:B,"")} -> #NAME?
G717: FALSE | K717: =J717-I717+1 -> 1 | O717: {=_xludf.XLOOKUP(csrd!N717,industries!A:A,industries!B:B,"")} -> #NAME?
... G721: FALSE | K721: =J721-I721+1 -> 1 | O721: {=_xludf.XLOOKUP(csrd!N721,industries!A:A,industries!B:B,"")} -> #NAME?
A722: ⬆️Please enter all already published reports above (english versions only) ⬆️
A723: Following reports will be available soon:
C724: Sylvania Group | D724: n.a | E724: Hungary | F724: 45823 | G724: TRUE | K724: =J724-I724+1 -> 1 | O724: {=_xludf.XLOOKUP(csrd!N724,industries!A:A,industries!B:B,"")} -> #NAME?
C725: Dr. Miele Cosmed Group | D725: n.a. | E725: Poland | F725: 45763 | G725: TRUE | H725: BDO | I725: 48 | J725: 158 | K725: =J725-I725+1 -> 111 | L725: no english version | O725: {=_xludf.XLOOKUP(csrd!N725,industries!A:A,industries!B:B,"")} -> #NAME?
C726: KELAG | D726: n.a. | E726: Austria | F726: 45764 | G726: TRUE | H726: KPMG | I726: 46 | J726: 286 | K726: =J726-I726+1 -> 241 | L726: no english AR yet | O726: {=_xludf.XLOOKUP(csrd!N726,industries!A:A,industries!B:B,"")} -> #NAME?
C727: Semapa-Sociedade de Investimento e Gestao | D727: PTSEM0AM0004 | E727: Portugal | F727: 45777 | G727: FALSE | H727: KPMG | I727: 81 | J727: 353 | K727: =J727-I727+1 -> 273 | L727: no english report yet | O727: {=_xludf.XLOOKUP(csrd!N727,industries!A:A,industries!B:B,"")} -> #NAME?
C728: Floridienne | D728: BE0003215143 | E728: Belgium | F728: 45777 | G728: FALSE | H728: EY | I728: 70 | J728: 137 | K728: =J728-I728+1 -> 68 | L728: no english report yet | O728: {=_xludf.XLOOKUP(csrd!N728,industries!A:A,industries!B:B,"")} -> #NAME?
C729: Ad Capital AG | D729: DE0005214506 | E729: Germany | G729: FALSE | K729: =J729-I729+1 -> 1 | L729: no english report yet | O729: {=_xludf.XLOOKUP(csrd!N729,industries!A:A,industries!B:B,"")} -> #NAME?
C730: Bang and Olufsen | D730: DK0010218429 | E730: Denmark | G730: FALSE | K730: =J730-I730+1 -> 1 | L730: no annual report 24/25 yet | O730: {=_xludf.XLOOKUP(csrd!N730,industries!A:A,industries!B:B,"")} -> #NAME?
C731: APPLUS SERVICES, S.A. | D731: ES0105022000 | E731: Spain | G731: FALSE | K731: =J731-I731+1 -> 1 | L731: no annual report 2024 yet | O731: {=_xludf.XLOOKUP(csrd!N731,industries!A:A,industries!B:B,"")} -> #NAME?
C732: Talgo SA | G732: FALSE | K732: =J732-I732+1 -> 1 | L732: no annual report 2024 yet | O732: {=_xludf.XLOOKUP(csrd!N732,industries!A:A,industries!B:B,"")} -> #NAME?
C733: Uponor Oyj | G733: FALSE | K733: =J733-I733+1 -> 1 | L733: no annual report 2024 yet | O733: {=_xludf.XLOOKUP(csrd!N733,industries!A:A,industries!B:B,"")} -> #NAME?
C734: Banca Transilvania | D734: ROTLVAACNOR1 | E734: Romania | G734: FALSE | I734: 1 | J734: 280 | K734: =J734-I734+1 -> 280 | L734: Raport-Sustenabilitate.pdf | O734: {=_xludf.XLOOKUP(csrd!N734,industries!A:A,industries!B:B,"")} -> #NAME?
C735: DKB | E735: Germany | G735: FALSE | K735: =J735-I735+1 -> 1 | L735: https://dok.dkb.de/pdf/gb_2024.pdf | O735: {=_xludf.XLOOKUP(csrd!N735,industries!A:A,industries!B:B,"")} -> #NAME?
C736: Azienda Trasporti Milanesi (ATM) | D736: n.a. | E736: Italy | G736: FALSE | L736: no english version yet | O736: {=_xludf.XLOOKUP(csrd!N736,industries!A:A,industries!B:B,"")} -> #NAME?
C737: AXWAY SOFTWARE SA | G737: FALSE | K737: =J737-I737+1 -> 1 | O737: {=_xludf.XLOOKUP(csrd!N737,industries!A:A,industries!B:B,"")} -> #NAME?
C738: Hrvatski Telekom | D738: HRHT00RA0005 | E738: Croatia | F738: 46105 | G738: FALSE | H738: Deloitte | I738: 37 | J738: 132 | K738: =J738-I738+1 -> 96 | L738: https://static.hrvatskitelekom.hr/webresources/tht/pdf/investitori/izvjesca/ANNUAL_REPORT_ENG_2025.pdf?_gl=1*1fcvs54*_up*MQ..*_ga*Nzc3MTIyNDguMTc3NDUxNzA2NQ..*_ga_85807GK74E*czE3NzQ1MTcwNjQkbzEkZzAkdDE3NzQ1MTcwNjQkajYwJGwwJGgxNTg4NzA2MTUx | N738: Telecommunication Services | O738: {=_xludf.XLOOKUP(csrd!N738,industries!A:A,industries!B:B,"")} -> #NAME?
K739: =J739-I739+1 -> 1 | O739: {=_xludf.XLOOKUP(csrd!N739,industries!A:A,industries!B:B,"")} -> #NAME?
G740: FALSE | K740: =J740-I740+1 -> 1 | O740: {=_xludf.XLOOKUP(csrd!N740,industries!A:A,industries!B:B,"")} -> #NAME?
G741: FALSE | K741: =J741-I741+1 -> 1 | O741: {=_xludf.XLOOKUP(csrd!N741,industries!A:A,industries!B:B,"")} -> #NAME?
G742: FALSE | K742: =J742-I742+1 -> 1 | O742: {=_xludf.XLOOKUP(csrd!N742,industries!A:A,industries!B:B,"")} -> #NAME?
G743: FALSE | K743: =J743-I743+1 -> 1 | O743: {=_xludf.XLOOKUP(csrd!N743,industries!A:A,industries!B:B,"")} -> #NAME?
G744: FALSE | K744: =J744-I744+1 -> 1 | O744: {=_xludf.XLOOKUP(csrd!N744,industries!A:A,industries!B:B,"")} -> #NAME?
G745: FALSE | K745: =J745-I745+1 -> 1 | O745: {=_xludf.XLOOKUP(csrd!N745,industries!A:A,industries!B:B,"")} -> #NAME?
...

Sheet Passwords

Sheet non-csrd (other) reports
A1: company | B1: isin | C1: country | D1: publication date | E1: claim full CSRD | F1: link | G1: SASB industry (SICS® Industries) | H1: Comment
A2: A.S. Création Tapeten AG | B2: DE000A1TNNN5 | C2: Germany | D2: 2025-27-03 | E2: TRUE | F2: https://www.as-creation.com/fileadmin/05_Nachhaltigkeit/AS_Nachhaltigkeitsbericht2024.pdf | G2: Building Products & Furnishings | H2: Building Products & Furnishings
A3: AB Volvo | B3: SE0000115446 | C3: Sweden | D3: 45715 | E3: FALSE | F3: https://www.volvogroup.com/content/dam/volvo-group/markets/master/events/2025/annual-reports/volvo-group-annual-report-2024.pdf | G3: Processed Foods | H3: Processed Foods
A4: ABB | B4: CH0012221716 | C4: Switzerland | D4: 45714 | E4: FALSE | F4: https://search.abb.com/library/Download.aspx?DocumentID=9AKK108470A7211&LanguageCode=en&DocumentPartId=&Action=Launch | G4: Electrical & Electronic Equipment | H4: Electrical & Electronic Equipment
A5: AdCapital AG | B5: DE0005214506 | C5: Germany | E5: FALSE | F5: https://www.adcapital.de/fileadmin/Dokumente/PDF/Finanzberichte/2025/ADCAPITAL_GB24_250513.pdf | G5: Industrial Machinery & Goods | H5: Industrial Machinery & Goods
A6: AGCO | B6: US0010841023 | C6: USA | E6: FALSE | F6: https://www.agcocorp.com/content/dam/public/agco-corp-v2/en/sustainability/sustainability-report-2024.pdf | G6: Agricultural Products | H6: Agricultural Products
A7: Ahlsell | B7: SE0009155005 | C7: Denmark | E7: FALSE | F7: ahlsellgroup.com/documentViewer?url=https%3A%2F%2Fcdn.sanity.io%2Ffiles%2Ftin4ef4v%2Fcorpsite-dev%2F5558eccf5a3496eec407f3e6290819d9345726c3.pdf | G7: Industrial Machinery & Goods | H7: Industrial Machinery & Goods
A8: Ahlsell Danmark A/S | B8: DK0010245661 | C8: Denmark | E8: FALSE | F8: ahlsellgroup.com/documentViewer?url=https%3A%2F%2Fcdn.sanity.io%2Ffiles%2Ftin4ef4v%2Fcorpsite-dev%2F5558eccf5a3496eec407f3e6290819d9345726c3.pdf
A9: Ahsell | B9: SE0009155005 | C9: Sweden | E9: FALSE | F9: https://www.ahlsellgroup.com/documentViewer?url=https%3A%2F%2Fcdn.sanity.io%2Ffiles%2Ftin4ef4v%2Fcorpsite-dev%2F5558eccf5a3496eec407f3e6290819d9345726c3.pdf | G9: Industrial Machinery & Goods | H9: Industrial Machinery & Goods
A10: Aktiebolaget SKF | B10: SE0000108227 | C10: Sweden | E10: FALSE | F10: CSRD (grosse entreprises doivent y répondre)
A11: Alpiq | B11: CH1184694755 | C11: Switzerland | D11: 45714 | E11: FALSE | F11: https://reports.alpiq.com/24/app/uploads/Annual_Report_2024_en.pdf | G11: Electric Utilities & Power Generators | H11: Electric Utilities & Power Generators
A12: Altresmedia Corporacion | B12: ES0109427734 | C12: Spain | D12: 45715 | E12: FALSE | F12: consolidated_non-financial_information_and_sustainability_statement_2024.pdfe | G12: Media & Entertainment | H12: Media & Entertainment
A13: Andritz | B13: AT0000730007 | C13: Austria | D13: 45720 | E13: FALSE | F13: https://www.andritz.com/resource/blob/620974/e66acf15517f7bab56818dbc86194b84/andritz-non-financial-statement-2024-e-data.pdf | G13: Chemicals | H13: Chemicals
A14: Andritz AG | B14: AT0000730007rt | C14: Austria | E14: FALSE | F14: https://www.safran-group.com/download/media/447681 | G14: Industrial Machinery & Goods | H14: Industrial Machinery & Goods
A15: Aperam | B15: U0569974404 | C15: Luxembourg | E15: FALSE | F15: https://www.aperam.com/sites/default/files/documents/AnnualReport_2024_compressed.pdf | G15: Metals & Mining | H15: Metals & Mining
A16: APERAM SA | B16: LU0569974404 | C16: Luxembourg | E16: FALSE | F16: https://www.aperam.com/sites/default/files/documents/AnnualReport_2024_compressed.pdf | G16: Metals & Mining | H16: Metals & Mining
A17: Arbejdernes Landsbank | B17: - | C17: Denmark | D17: 45693 | E17: FALSE | F17: https://attachment.news.eu.nasdaq.com/a8f76c062438e9d9c8b4f64863f68786c | G17: Commercial Banks | H17: Commercial Banks
A18: Argan | B18: FR0010481960 | C18: France | D18: 45713 | E18: FALSE | F18: https://www.argan.fr/wp-content/uploads/2024/06/Argan-Rapport-ESG-2024_Web-1.pdf | G18: Asset Management & Custody Activities | H18: Asset Management & Custody Activities
A19: Arla | B19: cooperative | C19: Denmark | D19: 45707 | E19: FALSE | F19: https://www.arla.com/493f52/globalassets/arla-global/company---overview/investor/annual-reports/2024/arla-annual-report-2024-uk2.pdf | G19: Meat, Poultry & Dairy | H19: Meat, Poultry & Dairy
A20: ASA International Group PLC | B20: GB00BDFXHW57 | C20: United Kingdom | E20: FALSE | F20: https://www.asa-international.com/media/2468/asa-ar2024-interactive.pdf | G20: Consumer Finance | H20: Consumer Finance
A21: Atlas Copco | B21: Tr | C21: Sweden | E21: FALSE | F21: https://www.atlascopcogroup.com/content/dam/atlas-copco/group/documents/investors/financial-publications/english/20250320-annual-report-2024-incl-sustainability-report-and-corporate-governance-report-copy-of-the-official-ESEF-format.pdf.coredownload.inline.pdf
A22: Atresmedia | B22: ES0109427734 | C22: Spain | D22: 45726 | E22: FALSE | F22: https://www.atresmediacorporacion.com/documents/2025/05/06/C6761BBB-B974-4095-AB3F-21AF9679814B/consolidated_non-financial_information_and_sustainability_statement_2024.pdf | G22: Telecommunication Services | H22: Telecommunication Services
A23: BANCA TRANSILVANIA SA | B23: ROTLVAACNOR1 | C23: Romania | E23: FALSE | F23: https://www.bancatransilvania.ro/files/app/media/relatii-investitori/environmental-social-governance-en/reports/2024/Sustainability-Report.pdf | G23: Commercial Banks | H23: Commercial Banks
A24: Bankinter | B24: ES0113679I37 | C24: Spain | D24: 45709 | E24: FALSE | F24: https://www.bankinter.com/file_source2/webcorporativa/estaticos/pdf/informacion-corporativa/banca-sostenible/informes-anuales/Estado_de_informacion_no_financiera_e_informacion_de_sostenibilidad_2024.pdf | G24: Commercial Banks | H24: Commercial Banks
A25: Banque Internationale à Luxembourg | B25: n.a. | C25: Luxembourg | D25: 45772 | E25: TRUE | F25: https://www.bil.com/Documents/brochures/Sustainability-report-2024.pdf | G25: Commercial Banks | H25: Commercial Banks
A26: Beiersdorf AG | B26: DE0005200000 | C26: Germany | D26: 45715 | E26: TRUE | F26: https://reports.beiersdorf.com/annual-report/2024/_assets/downloads/entire-beiersdorf-ar24.pdf?h=26S4OCM9 | G26: Household & Personal Products | H26: Household & Personal Products
A27: Beijer Alma | B27: SE0011090547 | C27: Sweden | D27: 45756 | E27: TRUE | F27: Beijer Alma annual report and sustainability report 2024 | G27: Industrial Machinery & Goods | H27: Industrial Machinery & Goods
A28: Bertrandt Aktiengesellschaft | B28: DE0005232805 | C28: Germany | D28: 45638 | E28: FALSE | F28: https://www.bertrandt.com/fileadmin/files/files/00_Unternehmen/01_Investor_Relations/03_Finanzberichte/GJ_23-24/annual_report_fy_2023-2024_bertrandt_.pdf | G28: Professional & Commercial Services | H28: Professional & Commercial Services
A29: Bidfood | B29: - | C29: Netherlands | D29: 45691 | E29: TRUE | F29: https://view.publitas.com/bidfood/duurzaamheidsverslag-2024-bidfood/page/117 | G29: Food Retailers & Distributors | H29: Food Retailers & Distributors
A30: Boliden | C30: Sweden | E30: FALSE | F30: https://investors.boliden.com/sites/boliden-ir/files/pr/202503192744-1.pdf
A31: Cancom | B31: DE0005419105 | C31: Germany | E31: FALSE | F31: omext.cancom.de/dam/?mdocs-file=19622&_gl=1*woc301*_gcl_au*ODg0ODU4NTU4LjE3NDg5NTgyNjc.*_ga*MTEzNjQ0MTUzMy4xNzQ4OTU4MjY4*_ga_LQPDT87YP2*czE3NDg5NTgyNjckbzEkZzEkdDE3NDg5NTgzMjgkajU5JGwwJGgw | G31: Software & IT Services | H31: Software & IT Services
A32: Cellnex | B32: ES0105066007 | C32: Spain | D32: 45714 | E32: FALSE | F32: https://informeanualintegrado.cellnex.com/files/2024/Informe_Anual_Integrado_2024_EN.pdf | G32: Telecommunication Services | H32: Telecommunication Services
A33: Cemex | B33: EST01PA00013 | C33: Spain | E33: FALSE | F33: cemex-integrated-report-2024-eng | G33: Construction Materials | H33: TCFD
A34: Cenit | B34: DE0005407100 | C34: Germany | E34: FALSE | F34: https://www.cenit.com/fileadmin/Media/cenit/investorrelations/pdf/reports/annual/Financial_Report_2024.pdf | G34: Software & IT Services | H34: seperate SR, https://www.cenit.com/fileadmin/Media/cenit/investorrelations/pdf/reports/sustainability/Sustainability-Report_2024_en.pdf
A35: CEWE Stiftung & Co. KGaA | B35: DE0005403901 | C35: Germany | D35: 45743 | E35: FALSE | F35: https://ir.cewe.de/websites/cewe/English/0/welcome-to-investor-relations-of-cewe_.html | G35: Media & Entertainment | H35: The implementation of reporting according to ESRS is currently in progress within the CEWE Group
A36: CMB.TECH NV | B36: BE0003816338 | C36: Belgium | E36: FALSE | F36: https://cmb.tech/public/242460_CMBTECH_AR_EN_Interactive.pdf | H36: "will only report Sustainability and Taxonomy-related information on a voluntary and case-by-case basis"
A37: Colruyt | B37: BE0974256852 | C37: Belgium | E37: FALSE | F37: Annual report with sustainability reporting 2023/24 | G37: Food Retailers & Distributors | H37: SDG
A38: CPI Property Group | B38: LU0251710041 | C38: Luxembourg | E38: FALSE | F38: https://cpipg.com/storage/app/uploads/public/67f/cb4/8d4/67fcb48d446a2161730542.pdf | G38: Real Estate | H38: seperate SR
A39: crh | B39: IE0001827041 | C39: Ireland | E39: FALSE | F39: https://www.crh.com/media/5661/crh-2024-sustainability-performance-report_final_interactive.pdf | G39: Construction Materials
A40: Dalata Hotel Group | B40: IE00BJMZDW83 | C40: Ireland | D40: 45722 | E40: FALSE | F40: https://dalatahotelgroup.com/wp-content/uploads/2025/03/2024-annual-report-and-accounts.xhtml | G40: Hotels & Lodging | H40: only Website, no online reader or pdf download with pages
A41: dcc | B41: IE0002424939 | C41: Ireland | E41: FALSE | F41: dcc-sustainability-report-2024.pdf | G41: Oil & Gas – Refining & Marketing
A42: Deutsche Kreditbank (DKB AG) | B42: n.a. | C42: Germany | D42: 45733 | E42: FALSE | F42: https://dok.dkb.de/pdf/gb_2024.pdf | G42: Commercial Banks | H42: in German
A43: Djursland Bank | B43: DK0060136273 | C43: Denmark | D43: 45693 | E43: FALSE | F43: https://attachment.news.eu.nasdaq.com/a8b79d092e9857d10dbdbb63613d895f4 | G43: Commercial Banks | H43: in Danish
A44: dm-drogerie markt GmbH & Co. KG | B44: - | C44: Germany | D44: 45610 | E44: FALSE | F44: https://content.services.dmtech.com/rootpage-dm-shop-de-de/resource/blob/2806786/ac37ed5bb54ff897131b832bf6a326e6/nachhaltigkeitsbericht-download-neu-data.pdf | G44: Multiline and Specialty Retailers & Distributors | H44: no full compliance
A45: EFG International | B45: n.a. | C45: Switzerland | D45: 45715 | E45: FALSE | F45: https://www.efginternational.com/doc/jcr:13a3c925-3ae3-447a-8e92-d1641d864feb/Sustainability%20Report%202024.pdf/lang:en/Sustainability%20Report%202024.pdf | G45: Commercial Banks | H45: no compliance
A46: Electrolux | B46: SE0016589188 | C46: Sweden | D46: 45708 | E46: FALSE | F46: https://www.electroluxgroup.com/wp-content/uploads/sites/2/2025/02/electrolux-Annual-Report-2024-250220.pdf | G46: Appliance Manufacturing | H46: voluntary partly adoption
A47: Embla Medical | B47: IS0000000040 | C47: Iceland | D47: 45693 | E47: TRUE | F47: https://media.ossur.com/image/upload/documents/corporate/Quarterly%20Reports/2024/2024%20Annual%20Report.pdf | G47: Biotechnology & Pharmaceuticals
A48: Energinet | B48: n.a. | C48: Denmark | E48: TRUE | F48: https://en.energinet.dk/media/5qgdbkxd/arsrapport-2024-ny-1.pdf | G48: Electric Utilities & Power Generators | H48: in Danish
A49: Epiroc | B49: SE0015658109 | C49: Sweden | D49: 45736 | E49: FALSE | F49: https://www.epirocgroup.com/content/dam/epiroc/corporate/documents/investors/annual-report/2024/Epiroc%20Annual%20and%20Sustainability%20Report-2024.pdf | G49: Industrial Machinery & Goods | H49: CSRD structured report but no claims of "in accordance"
A50: EQT AB | B50: SE0012853455 | C50: Sweden | D50: 45729 | E50: FALSE | F50: https://eqtgroup.com/shareholders/financial-calendar/annual-and-sustainability-report-2024 | G50: Asset Management & Custody Activities | H50: partial voluntary compliance
A51: Ericsson | B51: SE0000108656 | C51: Sweden | D51: 45716 | E51: FALSE | F51: https://www.ericsson.com/492c74/assets/local/investors/documents/2024/sustainability-and-corporate-responsibility-report-2024-en.pdf | G51: Hardware | H51: Content-wise aligned to CSRD/ESRS but no claims of "in accordance"
A52: Essity AB | B52: SE0009922156 | C52: Sweden | D52: 45719 | E52: FALSE | F52: Essity | Annual Report 2024 | G52: Household & Personal Products | H52: partial voluntary adoption
A53: EVN | B53: AT0000741053 | C53: Austria | D53: 45642 | E53: FALSE | F53: https://www.evn.at/getmedia/25e28ce2-db3c-49ae-ab23-fd39b2b8d412/EVN-Full-Report-2023-24_online.pdf | G53: Solar Technology & Project Developers | H53: in preparation for CSRD
A54: EVN AG | B54: AT0000741053 | C54: Austria | D54: 45643 | E54: TRUE | F54: https://www.evn.at/getmedia/25e28ce2-db3c-49ae-ab23-fd39b2b8d412/EVN-Full-Report-2023-24_online.pdf | G54: Electric Utilities & Power Generators | H54: in preparation for CSRD
A55: EVN AG | B55: AT0000741053 | C55: Austria | D55: 2024-21-17 | E55: FALSE | F55: https://www.evn.at/getmedia/25e28ce2-db3c-49ae-ab23-fd39b2b8d412/EVN-Full-Report-2023-24_online.pdf | G55: Electric Utilities & Power Generators | H55: only structure; explicitly claiming no compliance
A56: Experian | B56: GB00B19NLV48 | C56: United Kingdom | E56: FALSE | F56: experian_annual_report_2024_web.pdf | G56: Professional & Commercial Services
A57: Fabege | B57: SE0011166974 | C57: Sweden | D57: 45733 | E57: FALSE | F57: https://mb.cision.com/Main/1568/4119775/3324909.pdf | G57: Real Estate Services | H57: no full compliance
A58: FC St. Pauli | B58: - | C58: Germany | D58: 45722 | E58: FALSE | F58: https://www.fcstpauli.com/media/202012/fcsp-nachhaltigkeitsbericht-23_24.pdf?utm_source=website&utm_medium=fcsp&utm_campaign=QR-Code+FC+St.+Pauli+Nachhaltigkeitsbericht+Saison+23%2F24 | G58: Toys & Sporting Goods | H58: no compliance
A59: Flughafen Wien AG | B59: AT00000VIE62 | C59: Austria | E59: FALSE | F59: https://www.viennaairport.com/jart/prj3/va/uploads/data-uploads/IR/2025/VIE_JFB_2024_EN.pdf | G59: Airlines | H59: in preparation for CSRD
A60: FNN | B60: IT0000060886 | C60: Italy | E60: FALSE | F60: https://www.fnmgroup.it/wp-content/uploads/2025/04/Relazione-Finanziaria-31.12.24-FINALE_COMPLETO-2.pdf | G60: Rail Transportation | H60: only in italian
A61: Fraport | B61: DE0005773303 | C61: Germany | D61: 45734 | E61: TRUE | F61: https://www.fraport.com/en/investors/publications-events.html | G61: Professional & Commercial Services | H61: Partial application
A62: FrieslandCampina | B62: - | C62: Netherlands | D62: 45340 | E62: TRUE | F62: https://www.frieslandcampina.com/uploads/2025/02/FrieslandCampina-Annual-Report-2024.pdf | G62: Meat, Poultry & Dairy | H62: voluntary partly adoption
A63: Fuchs Petrolub | B63: DE000A3E5D56 | C63: Germany | D63: 45737 | E63: TRUE | F63: https://fuchs.azureedge.net/fileadmin/Home/Investor_Relations/Geschaeftsbericht/Zwischenbericht/2025_24_/FPL_GB24_englisch_final_interaktiv_geschuetzt__1_.pdf | G63: Chemicals | H63: partial compliance preparing for full compliance
A64: Givaudan | B64: CH0010645932 | C64: Switzerland | D64: 45681 | E64: TRUE | F64: https://www.givaudan.com/sites/givaudanweb.int/files/2025-01/giv-2024-integrated-report_4.pdf | G64: Chemicals
A65: Glanbia | B65: IE0000669501 | C65: Ireland | E65: FALSE | F65: https://glanbia-plc.pid2-e1.investis.com/sites/glanbia-plc/files/glanbia/sustainability/reporting-centre/sustainability-report-2024.pdf | G65: Meat, Poultry & Dairy
A66: Green Landscaping Group | B66: SE0010985028 | C66: Sweden | E66: FALSE | F66: https://www.greenlandscaping.com/files/mfn/561b2454-c986-4de5-ac6e-7194d0096a9e/gl-group-ar24-english.pdf | G66: Professional & Commercial Services | H66: in preperation
A67: Grenke | B67: DE000A161N30 | C67: Germany | D67: 45729 | E67: FALSE | F67: https://media.grenke.com/original/gallery/12428/files/original/d1b94364-037f-49ee-988f-ff4a211fbf72.pdf | G67: Hardware | H67: partial application
A68: H&M | B68: SE0000106270 | C68: Sweden | E68: FALSE | F68: https://hmgroup.com/wp-content/uploads/2025/03/HM-Group-Annual-and-sustainability-report-2024.pdf | G68: Apparel, Accessories & Footwear | H68: only structure; explicitly claiming no compliance
A69: Hamburger Hafen und Logistics | B69: DE000A0S8488 | C69: Germany | D69: 45742 | E69: FALSE | F69: https://report.hhla.de/annual-report-2024/_assets/downloads/HHLA_2024_AR_Annual-Report.pdf?h=aXymyQoe | G69: Professional & Commercial Services | H69: no CSRD compliance (but GRI reporting)
A70: Hannover Re | B70: DE0008402215 | C70: Germany | D70: 45729 | E70: FALSE | F70: https://d1qnw94usouwub.cloudfront.net/asset/533267266226/document_ba3r40ktgd3617as47ud9q8l7e?content-disposition=inline | G70: Insurance | H70: partial conformity with CSRD
A71: Heidelberg Materials | B71: DE0006047004 | C71: Germany | D71: 45737 | E71: FALSE | F71: https://www.heidelbergmaterials.com/sites/default/files/2025-03/HM_ASR24_en.pdf | G71: Construction Materials | H71: preparing for full compliance
A72: Hella | B72: DE000A13SX22 | C72: Germany | D72: 45729 | E72: FALSE | F72: https://www.hella.com/forvia-com/assets/documents/HELLA_Annual_Report_FY2024_secured.pdf | G72: Auto Parts | H72: partial application of ESRS
A73: Hexagon | B73: SE0015961909 | C73: Sweden | D73: 45743 | E73: FALSE | F73: https://vp208.alertir.com/afw/files/press/hexagon/202503255363-1.pdf | G73: Software & IT Services | H73: no full compliance
A74: Hilti | B74: CH0384125123 | C74: Liechtenstein | D74: 45730 | E74: TRUE | F74: https://www.hilti.group/content/dam/documents/Media-Release/company-report/hilti-sustainability-report.pdf#page=1 | G74: Industrial Machinery & Goods | H74: standalone SR
A75: Holcim | B75: CH0012214059 | C75: Switzerland | D75: 45716 | E75: FALSE | F75: https://www.holcim.com/sites/holcim/files/docs/28022025-finance-holcim-fy-2024-report-full-en.pdf | G75: Construction Materials | H75: voluntary adoption
A76: Holme AB | B76: SE0011090000 | C76: Sweden | E76: FALSE | F76: 202503067048-1.pdf | G76: Pulp & Paper Products | H76: GRI
A77: Holmen Aktiebolag | B77: SE0011090018 | C77: Sweden | E77: FALSE | F77: https://vp165.alertir.com/afw/files/press/holmen/202503067048-1.pdf | H77: GRI
A78: HUGO BOSS | B78: DE000A1PHFF7 | C78: Germany | D78: 45729 | E78: TRUE | F78: https://annualreport-2024.hugoboss.com/_assets/downloads/entire-hb-ar24.pdf | G78: Apparel, Accessories & Footwear | H78: Partial application
A79: Hugo Boss | B79: DE000A1PHFF7 | C79: Germany | D79: 45729 | E79: FALSE | F79: https://group.hugoboss.com/fileadmin/media/hbnews/user_upload/Investor_Relations/Finanzberichte/2024/HUGO_BOSS_Annual_Report_2024.pdf | G79: Apparel, Accessories & Footwear | H79: partial application
A80: Hypoport SE | B80: DE0005493365 | C80: Germany | E80: FALSE | F80: https://www.hypoport.com/wp-content/uploads/2025/03/20250320_CSR-Bericht_2024_ENG_v2.pdf | H80: seperate SR
A81: Indra | B81: ES0118594417 | C81: Spain | D81: 45714 | E81: FALSE | F81: https://www.cnmv.es/webservices/verdocumento/ver?e=QH4aUSp181UIFMrkvjZeFUvGON43wHHcXbrRTjRnO%2bCze5HLI2BThe6mgBjw3Gx%2f | G81: Software & IT Services | H81: in Spain
A82: Infineon Technologies | B82: DE0006231004 | C82: Germany | D82: 45622 | E82: FALSE | F82: https://www.infineon.com/dgdl/Infineon+Annual+Report+2024.pdf?fileId=8ac78c8b92bced620193694bfb970095 | G82: Semiconductors | H82: GRI and UN Global Compact Principles
A83: Ingka Group | B83: - | C83: Netherlands | D83: 45688 | E83: TRUE | F83: ingkagroup_annualsummaryandsustainabilityreport_fy24.pdf | G83: Multiline and Specialty Retailers & Distributors | H83: in preparation for csrd
A84: Investor | B84: SE0015811955 | C84: Sweden | D84: 45751 | E84: FALSE | F84: https://vp053.alertir.com/afw/files/press/investor/202504032251-1.pdf | G84: Asset Management & Custody Activities | H84: no full compliance
A85: Julius Meinl | B85: - | C85: Austria | D85: 45610 | E85: TRUE | F85: SUSTAINABILITY REPORT 2023 | Julius Meinl | G85: Building Products & Furnishings | H85: in preparation for csrd
A86: Karnov | B86: SE0012323715 | C86: Sweden | D86: 45747 | E86: FALSE | F86: https://www.karnovgroup.com/en/wp-content/uploads/sites/2/2025/02/karnovgroup-publication-of-karnov-groups-annual-report-and-sustainability-report-2024-250331.pdf | G86: Internet Media & Services | H86: in preparation for 2025 reporting
A87: Kloeckner & Co | B87: DE000KC01000 | C87: Germany | D87: 45728 | E87: FALSE | F87: https://www.kloeckner.com/dam/kco/files/en/publications/2025/Kloeckner_Co_AnnualReport2024.pdf | G87: Iron & Steel Producers | H87: partial application
A88: KomerÄnÃ­ banka, a.s. | B88: CZ0008019106 | C88: Czech Republic | D88: 45736 | E88: TRUE | F88: https://www.kb.cz/getmedia/9c7d4c2f-508b-4088-893e-7469b54d00d3/KB-Annual-Report-2024.pdf | G88: Commercial Banks | H88: no full compliance
A89: Kommunalbanken AS | B89: n.a. | C89: Norway | D89: 45729 | E89: FALSE | F89: https://www.kbn.com/globalassets/dokumenter/finansielle-rapporter/arsrapport/kbn-annual-report-2024.pdf | G89: Commercial Banks | H89: in preparation for CSRD
A90: KPMG Austria | B90: - | C90: Austria | D90: 45682 | E90: FALSE | F90: https://www.kpmg.at/upload/MCM/Publikationen/2025/nachhaltigkeitsbericht-2025.pdf | G90: Professional & Commercial Services | H90: in German, non-PIE
A91: KPMG Netherlands | B91: - | C91: Netherlands | D91: 45633 | E91: TRUE | F91: https://corporatereporting.kpmg.nl/external/asset/download/project/f97e730a-03ed-0000-6eb6-a2482757d6ff/name/KPMG_Integrated_report_2023_2024.pdf | G91: Professional & Commercial Services | H91: voluntary adoption
A92: KRONES | B92: DE0006335003 | C92: Germany | D92: 45736 | E92: TRUE | F92: https://www.krones.com/media/downloads/GB_2024_Konzern-NFE_e.pdf#page=76 | G92: Industrial Machinery & Goods | H92: Partial application
A93: L'Occitane International S.A. | B93: LU0501835309 | C93: France | E93: FALSE | F93: https://group.loccitane.com/sites/default/files/2024-07/20240726_ESG%20Report%20FY24_E.pdf | G93: Drug Retailers | H93: no comliance
A94: Lån & Spar Bank | B94: DK0010201532 | C94: Denmark | D94: 45693 | E94: FALSE | F94: https://attachment.news.eu.nasdaq.com/ad6a462df0f607ecb39937bd0061ab81a | G94: Commercial Banks | H94: in Danish
A95: Leifheit | B95: DE0006464506 | C95: Germany | D95: 45756 | E95: FALSE | F95: https://www.leifheit-group.com/app/uploads/2025/04/20250409_Leifheit_CSR_EN_PW.pdf | G95: Household & Personal Products | H95: seperate SR
A96: Lifco | B96: SE0015949201 | C96: Sweden | E96: FALSE | F96: https://network.s-z.se/app/uploads/sites/16/Lifco-annual-report-2024.pdf | G96: Medical Equipment & Supplies | H96: preparing for ESRS
A97: Logista Integral | B97: ES0105027009 | C97: Spain | E97: FALSE | F97: Consolidated Report - Logista (English Version) | H97: GRI
A98: Masterflex SE | B98: DE0005492938 | C98: Germany | E98: FALSE | F98: https://cdn.masterflexgroup.com/fileadmin/group/media/investor_relations/2024/masterflex_se-consolidated_non_financial_statement_2024_final.pdf | H98: seperate SR
A99: Masterplast | B99: HU0000093943 | C99: Hungary | E99: TRUE | F99: https://www.masterplastgroup.com/wp-content/uploads/2025/04/mp_csrd_eng.pdf | G99: Building Products & Furnishings | H99: seperate SR
A100: Matmut | B100: n.a. | C100: France | E100: FALSE | F100: https://www.matmut.fr/groupe-matmut/assets/img/decouvrir-le-groupe/documents/2025/etat-durabilite-matmut-2025.pdf | G100: Insurance | H100: only french and seperate SR
...

Sheet Hashencryption

Sheet industries
A1: SICS® Industries | B1: SICS® Sector
A2: Apparel, Accessories & Footwear | B2: Consumer Goods
A3: Appliance Manufacturing | B3: Consumer Goods
A4: Building Products & Furnishings | B4: Consumer Goods
A5: E-Commerce | B5: Consumer Goods
A6: Household & Personal Products | B6: Consumer Goods
A7: Multiline and Specialty Retailers & Distributors | B7: Consumer Goods
A8: Toys & Sporting Goods | B8: Consumer Goods
A9: Coal Operations | B9: Extractives & Mineral Processing
A10: Construction Materials | B10: Extractives & Mineral Processing
A11: Iron & Steel Producers | B11: Extractives & Mineral Processing
A12: Metals & Mining | B12: Extractives & Mineral Processing
... A78: Road Transportation | B78: Transportation

Sheet Pivot Table 2
A1: SASB industry (SICS® Industries) | B1: COUNTA of country
A2: Electric Utilities & Power Generators | B2: 33
A3: Industrial Machinery & Goods | B3: 29
A4: Software & IT Services | B4: 29
A5: Chemicals | B5: 26
A6: Engineering & Construction Services | B6: 26
A7: Telecommunication Services | B7: 24
A8: Biotechnology & Pharmaceuticals | B8: 20
A9: Electrical & Electronic Equipment | B9: 18
A10: Professional & Commercial Services | B10: 17
A11: Real Estate | B11: 15
A12: Food Retailers & Distributors | B12: 14
A13: Apparel, Accessories & Footwear | B13: 12
... A67: Grand Total | B67: 506

Sheet Detail6-Apparel, Accessories & 
A1: verified | B1: srn_id | C1: company | D1: isin | E1: country | F1: publication date | G1: claim full CSRD compliance | H1: auditor | I1: start PDF | J1: end PDF | K1: pages PDF | L1: link | M1: ESEF- tagged | N1: SASB industry (SICS® Industries) | O1: SASB sector (SICS® Sectors)
A2: yes | B2: kSkHNYvVe0 | C2: Pandora | D2: DK0060252690 | E2: Denmark | F2: 45693 | G2: TRUE | H2: EY | I2: 47 | J2: 101 | K2: 55 | L2: https://ml-eu.globenewswire.com/Resource/Download/edd04a03-bc89-4cc9-8924-4439f5efd4b0 | N2: Apparel, Accessories & Footwear | O2: Consumer Goods
A3: yes | B3: jtQIdIgNWF | C3: adidas | D3: DE000A1EWWW0 | E3: Germany | F3: 45721 | G3: TRUE | H3: PwC | I3: 140 | J3: 357 | K3: 218 | L3: https://report.adidas-group.com/2024/en/_assets/downloads/annual-report-adidas-ar24.pdf | N3: Apparel, Accessories & Footwear | O3: Consumer Goods
A4: yes | B4: MxYEBqpCCD | C4: Inditex | D4: ES0148396007 | E4: Spain | F4: 45728 | G4: TRUE | H4: EY | I4: 86 | J4: 381 | K4: 296 | L4: https://www.inditex.com/itxcomweb/api/media/604197b9-50de-4f4f-ab84-c1e379cb3fd0/Inditex_Group_Annual_Report_2024.pdf?t=1741989136588 | N4: Apparel, Accessories & Footwear | O4: Consumer Goods
A5: yes | B5: bML0strkox | C5: Puma | D5: DE0006969603 | E5: Germany | F5: 45728 | G5: TRUE | H5: KPMG | I5: 52 | J5: 195 | K5: 144 | L5: https://about.puma.com/sites/default/files/financial-report/2024/puma-annual-report-2024-en-final_0.pdf | N5: Apparel, Accessories & Footwear | O5: Consumer Goods
A6: yes | B6: u2gOgWBUGq | C6: Kering | D6: FR0000121485 | E6: France | F6: 45731 | G6: TRUE | H6: Deloitte & PwC | I6: 159 | J6: 268 | K6: 110 | L6: https://www.kering.com/api/download-file/?path=DEU_EN_2024_interactif_26c8d4882e.pdf | N6: Apparel, Accessories & Footwear | O6: Consumer Goods
A7: yes | B7: 58xSrTRKFO | C7: LVMH | D7: FR0000121014 | E7: France | F7: 45742 | G7: TRUE | H7: Deloitte | I7: 47 | J7: 240 | K7: 194 | L7: https://lvmh-com.cdn.prismic.io/lvmh-com/Z-PY3HdAxsiBv6wN_UniversalRegistrationDocument2024.pdf | N7: Apparel, Accessories & Footwear | O7: Consumer Goods
A8: yes | B8: HD2Up603Po | C8: Hermes | D8: FR0000052292 | E8: France | F8: 45743 | G8: TRUE | H8: PwC | I8: 49 | J8: 223 | K8: 175 | L8: https://assets-finance.hermes.com/s3fs-public/node/pdf_file/2025-03/1743171341/250328_hermes_urd2024_en.pdf?VersionId=ZZZMxGiUT7xHs0CZUKn6vrm0L1EvqtfS | N8: Apparel, Accessories & Footwear | O8: Consumer Goods
A9: yes | B9: OYQSokOV9z | C9: LPP | D9: PLLPP0000011 | E9: Poland | F9: 45750 | G9: TRUE | H9: Grant Thornton | I9: 58 | J9: 159 | K9: 102 | L9: https://wwwlpp62711ea95a.blob.core.windows.net/blobwwwlpp62711ea95a/wp-content/uploads/2025/04/Consolidated-annual-report-of-LPP-SA-Group-for-2024.pdf | N9: Apparel, Accessories & Footwear | O9: Consumer Goods
A10: yes | B10: IvAEvZB2Jr | C10: Salvatore Ferragamo | D10: IT0004712375 | E10: Italy | F10: 45763 | G10: TRUE | H10: KPMG | I10: 101 | J10: 276 | K10: 176 | L10: https://cdn.ferragamo.com/cdn/investor-relations/financial-documents/2024/en/Annualreport2024.pdf | N10: Apparel, Accessories & Footwear | O10: Consumer Goods
A11: yes | B11: G0tmEKzXxL | C11: Brunello Cucinelli | D11: IT0004764699 | E11: Italy | F11: 45729 | G11: TRUE | H11: PwC | I11: 79 | J11: 218 | K11: 140 | L11: https://investor.brunellocucinelli.com/yep-content/media/Consolidated_Financial_Statements_2024_including_Consolidated_Sustainability_Report.pdf | N11: Apparel, Accessories & Footwear | O11: Consumer Goods
A12: yes | C12: Smcp | D12: FR0013214145 | E12: France | F12: 45763 | G12: TRUE | H12: Deloitte | I12: 67 | J12: 179 | K12: 113 | L12: https://www.smcp.com/app/uploads/2025/04/smcp-2024-urd-en-mel.pdf | N12: Apparel, Accessories & Footwear | O12: Consumer Goods
A13: yes | C13: CCC | D13: PLCCC0000016 | E13: Poland | F13: 45775 | G13: TRUE | H13: EY | I13: 150 | J13: 318 | K13: 169 | L13: https://corporate.ccc.eu/en/download/pobierz/consolidated-directors-report-of-the-ccc-group-for-the-fiscal-year-2024 | N13: Apparel, Accessories & Footwear | O13: Consumer Goods

Sheet Detail4-Software & IT Services
A1: verified | B1: srn_id | C1: company | D1: isin | E1: country | F1: publication date | G1: claim full CSRD compliance | H1: auditor | I1: start PDF | J1: end PDF | K1: pages PDF | L1: link | M1: ESEF- tagged | N1: SASB industry (SICS® Industries) | O1: SASB sector (SICS® Sectors)
A2: yes | B2: U5qn8FYXmx | C2: WithSecure | D2: FI4000519228 | E2: Finland | F2: 45700 | G2: TRUE | H2: PwC | I2: 25 | J2: 100 | K2: 76 | L2: https://www.withsecure.com/content/dam/with-secure/en/investor/materials/WithSecure_Annual_Report_2024.pdf | N2: Software & IT Services | O2: Technology & Communications
A3: yes | B3: AaVQoDERvE | C3: NNIT | D3: DK0060580512 | E3: Denmark | F3: 45707 | G3: TRUE | H3: EY | I3: 35 | J3: 109 | K3: 75 | L3: https://www.nnit.com/media/50fpzrik/nnit-annual-report-2024.pdf | N3: Software & IT Services | O3: Technology & Communications
A4: yes | B4: 7ldgfxy05n | C4: SAP | D4: DE0007164600 | E4: Germany | F4: 45715 | G4: TRUE | H4: BDO | I4: 117 | J4: 230 | K4: 114 | L4: https://www.sap.com/docs/download/investors/2024/sap-2024-integrated-report.pdf | N4: Software & IT Services | O4: Technology & Communications
A5: yes | B5: fE6pnLGIhh | C5: Amadeus IT | D5: ES0109067019 | E5: Spain | F5: 45716 | G5: TRUE | H5: EY | I5: 1 | J5: 210 | K5: 210 | L5: https://corporate.amadeus.com/documents/en/investors/2024/corporate-governance/non-financial-information-2024.pdf | N5: Software & IT Services | O5: Technology & Communications
A6: yes | B6: 3DwvMhyRNU | C6: Tietoevry | D6: FI0009000277 | E6: Finland | F6: 45720 | G6: TRUE | H6: Deloitte | I6: 73 | J6: 151 | K6: 79 | L6: https://ar2024.tietoevry.com/siteassets/tietoevry_annual_report_2024.pdf | N6: Software & IT Services | O6: Technology & Communications
A7: yes | B7: 5xeBea8f7o | C7: Sopra Steria | D7: FR0000050809 | E7: France | F7: 45730 | G7: TRUE | H7: ACA Nexia & Saint Front | I7: 119 | J7: 262 | K7: 144 | L7: https://www.soprasteria.com/docs/librariesprovider2/sopra-steria-corporate/finance/rapports-financiers/sopra_steria_urd_2024_en_opti.pdf?sfvrsn=e57d27db_16 | N7: Software & IT Services | O7: Technology & Communications
A8: yes | B8: Ss1NQGLDMY | C8: Teleperformance | D8: FR0000051807 | E8: France | F8: 45722 | G8: TRUE | H8: PwC | I8: 93 | J8: 204 | K8: 112 | L8: https://www.tp.com/media/2balwxel/tp-2024-urd.pdf | N8: Software & IT Services | O8: Technology & Communications
A9: yes | B9: KVIUMb7Pwn | C9: Capgemini | D9: FR0000125338 | E9: France | F9: 45737 | G9: TRUE | H9: Forvis Mazars | I9: 139 | J9: 371 | K9: 233 | L9: https://investors.capgemini.com/en/file/28667?download=1 | N9: Software & IT Services | O9: Technology & Communications
A10: yes | B10: 9wHDxV0xAc | C10: Dassault Systèmes | D10: FR0014003TT8 | E10: France | F10: 45743 | G10: TRUE | H10: PwC | I10: 62 | J10: 226 | K10: 165 | L10: https://investor.3ds.com/static-files/f4610f80-970f-4a88-ab8e-0df492444765?_gl=1*vquc5h*_up*MQ..*_ga*MjA0MjE4MDg3MC4xNzQzMDY3OTQ2*_ga_DYJDKXYEZ4*MTc0MzA2Nzk0NS4xLjEuMTc0MzA2Nzk2Mi4wLjAuMA..*_ga_39DKQ0LYW1*MTc0MzA2Nzk0NS4xLjEuMTc0MzA2Nzk2Mi4wLjAuMA.. | N10: Software & IT Services | O10: Technology & Communications
A11: yes | B11: hJTtF7ZCHG | C11: CD PROJEKT | D11: PLOPTTC00011 | E11: Poland | F11: 45741 | G11: TRUE | H11: Grant Thornton | I11: 87 | J11: 144 | K11: 58 | L11: https://www.cdprojekt.com/en/wp-content/uploads-en/2025/03/management-board-report-on-cd-projekt-group-activities-in-2024.pdf#page=87 | N11: Software & IT Services | O11: Technology & Communications
A12: yes | B12: A3QGss28LW | C12: TKH | D12: NL0000852523 | E12: Netherlands | F12: 45727 | G12: TRUE | H12: EY | I12: 83 | J12: 157 | K12: 75 | L12: https://storage.tkhgroup.com/cms/assets/TKH_Annual_Report_2024_324a0e861e.pdf | N12: Software & IT Services | O12: Technology & Communications
A13: yes | B13: mvE4QBybG4 | C13: 74Software | D13: FR0011040500 | E13: France | F13: 45740 | G13: TRUE | H13: ACA Nexia & Forvis Mazars | I13: 61 | J13: 163 | K13: 103 | L13: https://www.74software.com/sites/default/files/financial_documents/2024%20-%20DEU%20-%20VEN%20-%2024%20mars.pdf | N13: Software & IT Services | O13: Technology & Communications
... A20: yes | B20: ZBx9ucQuu2 | C20: F-Secure | D20: FI4000519236 | E20: Finland | F20: 45715 | G20: TRUE | H20: PwC | I20: 27 | J20: 131 | K20: 105 | L20: https://storage.googleapis.com/inderes-widgets-prod-assets/fsecure/attachments/c5bb7309-905e-488c-ac41-8c51c664843d/f-secure-annual-report-2024.pdf | N20: Software & IT Services | O20: Technology & Communications
A21: yes | C21: Gofore | D21: FI4000283130 | E21: Finland | F21: 45736 | G21: TRUE | H21: EY | I21: 18 | J21: 96 | K21: 79 | L21: https://gofore.com/media/gofore-annual-report-2024.pdf | N21: Software & IT Services | O21: Technology & Communications
A22: yes | C22: Lectra | D22: FR0000065484 | E22: France | F22: 45744 | G22: TRUE | H22: PwC | I22: 45 | J22: 128 | K22: 84 | L22: https://www.lectra.com/sites/default/files/investors_files/LECTRA_-_Rapport_financier_annuel_2024_EN%20%285%29.pdf | N22: Software & IT Services | O22: Technology & Communications
A23: yes | C23: Modern Times Group (MTG) | D23: SE0018012494 | E23: Sweden | F23: 45750 | G23: TRUE | H23: PwC | I23: 128 | J23: 179 | K23: 52 | L23: https://mb.cision.com/Main/56/4130091/3366010.pdf | N23: Software & IT Services | O23: Technology & Communications
A24: yes | C24: Novabase SGPS | D24: PTNBA0AM0006 | E24: Portugal | F24: 45708 | G24: TRUE | H24: EY | I24: 35 | J24: 78 | K24: 44 | L24: https://content.novabase.com/storage/uploads/reports-accounts-2024-no-esef.pdf | N24: Software & IT Services | O24: Technology & Communications
A25: yes | C25: QT Group | D25: FI4000198031 | E25: Finland | F25: 45716 | G25: TRUE | H25: KPMG | I25: 18 | J25: 63 | K25: 46 | L25: https://www.qt.io/hubfs/_website/QtV2/QtV2%20Investors/2024/Annual%20Report/Qt-AnnualReport-2024-ENG.pdf?hsLang=en | N25: Software & IT Services | O25: Technology & Communications
A26: yes | C26: Siili Solutions | D26: FI4000043435 | E26: Finland | F26: 45701 | G26: TRUE | H26: KPMG | I26: 13 | J26: 35 | K26: 23 | L26: https://www.siili.com/hubfs/Siili%20Solutions%20Plc%20Annual%20Report%202024.pdf | N26: Software & IT Services | O26: Technology & Communications
A27: yes | C27: Unifieldpost Group | D27: BE0974371032 | E27: Belgium | F27: 45764 | G27: TRUE | H27: BDO | I27: 33 | J27: 129 | K27: 97 | L27: https://investors.unifiedpostgroup.com/static-files/b44551f7-3ad6-4037-b984-5acc801243c5 | N27: Software & IT Services | O27: Technology & Communications
A28: yes | C28: Virdien | D28: FR001400PVN6 | E28: France | F28: 45722 | G28: TRUE | H28: EY | I28: 61 | J28: 142 | K28: 82 | L28: https://www.viridiengroup.com/sites/default/files/2025-03/viridien_universal_registration_document_2024.pdf | N28: Software & IT Services | O28: Technology & Communications
A29: yes | C29: Bechtle | D29: DE0005158703 | E29: Germany | F29: 45730 | G29: TRUE | H29: Deloitte | I29: 107 | J29: 184 | K29: 78 | L29: https://www.bechtle.com/dam/jcr:f7605839-67f3-4064-a1ea-e109b3f7c2ce/bechtle_ag_annual_report_2024.pdf | N29: Software & IT Services | O29: Technology & Communications
A30: yes | C30: Ubisoft | D30: FR0000054470 | E30: France | F30: 45827 | G30: TRUE | H30: Forvis Mazars | I30: 131 | J30: 215 | K30: 85 | L30: https://staticctf.ubisoft.com/8aefmxkxpxwl/2jOPqNEzotGX0odqDUt5jr/57f0ba952c3be14b38ba97a02b17c119/Ent_AGM_2025.07.10_URD_GB_Interactif_def.pdf | N30: Software & IT Services | O30: Technology & Communications

Sheet Detail2-Water Utilities & Servi
A1: verified | B1: srn_id | C1: company | D1: isin | E1: country | F1: publication date | G1: claim full CSRD compliance | H1: auditor | I1: start PDF | J1: end PDF | K1: pages PDF | L1: link | M1: ESEF- tagged | N1: SASB industry (SICS® Industries) | O1: SASB sector (SICS® Sectors)
A2: yes | B2: OjlhED25YW | C2: Veolia | D2: FR0000124141 | E2: France | F2: 45727 | G2: TRUE | H2: KPMG & EY | I2: 175 | J2: 320 | K2: 146 | L2: https://www.veolia.com/sites/g/files/dvc4206/files/document/2025/03/Veolia_2024_URD.pdf | N2: Water Utilities & Services | O2: Infrastructure

Sheet Detail1-Aerospace & Defence
A1: verified | B1: srn_id | C1: company | D1: isin | E1: country | F1: publication date | G1: claim full CSRD compliance | H1: auditor | I1: start PDF | J1: end PDF | K1: pages PDF | L1: link | M1: ESEF- tagged | N1: SASB industry (SICS® Industries) | O1: SASB sector (SICS® Sectors)
A2: yes | B2: 7OXsmQaYdu | C2: Airbus | D2: NL0000235190 | E2: France | F2: 45748 | G2: TRUE | H2: EY | I2: 130 | J2: 238 | K2: 109 | L2: https://www.airbus.com/sites/g/files/jlcbta136/files/2025-04/Airbus%20Annual%20Report%202024.pdf | N2: Aerospace & Defence | O2: Resource Transformation
A3: yes | B3: sRSKwL2rFV | C3: Rheinmetall | D3: DE0007030009 | E3: Germany | F3: 45728 | G3: TRUE | H3: Deloitte | I3: 91 | J3: 151 | K3: 61 | L3: https://ir.rheinmetall.com/media/document/0138f185-ccd4-4521-837b-e49cb68730b5/assets/DE0007030009-JA-2024-EQ-E-00.pdf | N3: Aerospace & Defence | O3: Resource Transformation
A4: yes | B4: r0LxzBHtpA | C4: MTU Aero Engines | D4: DE000A0D9PT0 | E4: Germany | F4: 45741 | G4: TRUE | H4: KPMG | I4: 111 | J4: 213 | K4: 103 | L4: https://www.mtu.de/fileadmin/DE/5_Investoren/Financial_Report/MTUAeroEnginesAG_AnnualReport_2024_en_locked.pdf | N4: Aerospace & Defence | O4: Resource Transformation
A5: yes | B5: 9S7wNIrYn9 | C5: SAFRAN | D5: FR0000073272 | E5: France | F5: 45744 | G5: TRUE | H5: Forvis Mazars & EY | I5: 325 | J5: 448 | K5: 124 | L5: https://www.safran-group.com/download/media/447681 | N5: Aerospace & Defence | O5: Resource Transformation
A6: yes | B6: dEUrRs95vc | C6: Leonardo | D6: IT0003856405 | E6: Italy | F6: 45727 | G6: TRUE | H6: EY | I6: 84 | J6: 195 | K6: 112 | L6: https://www.leonardo.com/documents/15646808/28608810/2024+Integrated+Annual+Report.pdf?t=1741973243807 | N6: Aerospace & Defence | O6: Resource Transformation
A7: yes | B7: M2OHiF61FY | C7: FACC | D7: AT00000FACC2 | E7: Austria | F7: 45742 | G7: TRUE | H7: KPMG | I7: 23 | J7: 64 | K7: 42 | L7: https://www.facc.com/en/content/download/3113996/file/FA_0124_Geschaeftsbericht_EN_RZ_250325_FINAL.pdf | N7: Aerospace & Defence | O7: Resource Transformation
A8: yes | B8: 7v10GwEKdh | C8: Dassault Aviation | D8: FR0014004L86 | E8: France | F8: 45734 | G8: TRUE | H8: PwC & Forvis Mazars | I8: 90 | J8: 194 | K8: 105 | L8: https://www.dassault-aviation.com/wp-content/blogs.dir/2/files/2025/04/AR_2024_VA_BD.pdf | N8: Aerospace & Defence | O8: Resource Transformation
A9: yes | C9: Kongsberg Gruppen | D9: NO0003043309 | E9: Norway | F9: 45741 | G9: TRUE | H9: EY | I9: 40 | J9: 107 | K9: 68 | L9: https://www.kongsberg.com/globalassets/kongsberg-asa/5.-investor-relations/1.3.-reports-and-presentations/1.3.1.-annual-report/annual-report-2024/annual-report-2024-eng.pdf | N9: Aerospace & Defence | O9: Resource Transformation
A10: yes | C10: Saab | D10: SE0021921269 | E10: Sweden | F10: 45719 | G10: TRUE | H10: PwC | I10: 66 | J10: 145 | K10: 80 | L10: https://www.saab.com/globalassets/cision/documents/2025/20250303-saab-publishes-its-2024-annual-and-sustainability-report-en-0-4999946.pdf | N10: Aerospace & Defence | O10: Resource Transformation
A11: yes | C11: Thales | D11: FR0000121329 | E11: France | F11: 45755 | G11: TRUE | H11: PwC | I11: 143 | J11: 236 | K11: 94 | L11: https://www.thalesgroup.com/sites/default/files/database/document/2025-04/Universal%20Registration%20Document%202024%20-%20Thales_0.pdf | N11: Aerospace & Defence | O11: Resource Transformation
A12: yes | C12: Frequentis | D12: ATFREQUENT09 | E12: Austria | F12: 45772 | G12: TRUE | H12: BDO | I12: 40 | J12: 132 | K12: 93 | L12: https://www.frequentis.com/sites/default/files/support/2025-04/Frequentis_Annual_Report_2024.pdf | N12: Aerospace & Defence | O12: Resource Transformation

Sheet Chart1 Count of Companies by SA
A1: SASB sector | B1: Company Count
A2: Consumer Goods | B2: 42
A3: Extractives & Mineral Processing | B3: 45
A4: Financials | B4: 135
A5: Food & Beverage | B5: 50
A6: Health Care | B6: 43
A7: Infrastructure | B7: 100
A8: Renewable Resources & Alternative Energy | B8: 12
A9: Resource Transformation | B9: 97
A11: Services | B11: 39
A12: Technology & Communications | B12: 75
A13: Transportation | B13: 55
